Metadata-Version: 2.1
Name: json-html
Version: 0.0.2
Summary: Python code that translates JSON template to HTML
Home-page: https://github.com/AlexFlipnote/json_html.py
Author: AlexFlipnote
License: MIT
License-File: LICENSE
